README.txt
setup.py
Products/__init__.py
Products.plonehrm.egg-info/PKG-INFO
Products.plonehrm.egg-info/SOURCES.txt
Products.plonehrm.egg-info/dependency_links.txt
Products.plonehrm.egg-info/entry_points.txt
Products.plonehrm.egg-info/namespace_packages.txt
Products.plonehrm.egg-info/not-zip-safe
Products.plonehrm.egg-info/requires.txt
Products.plonehrm.egg-info/top_level.txt
Products/plonehrm/HISTORY.txt
Products/plonehrm/README.txt
Products/plonehrm/TODO.txt
Products/plonehrm/__init__.py
Products/plonehrm/config.py
Products/plonehrm/configure.zcml
Products/plonehrm/controlpanel.py
Products/plonehrm/deprecation.zcml
Products/plonehrm/events.py
Products/plonehrm/interfaces.py
Products/plonehrm/localroles.py
Products/plonehrm/migration.py
Products/plonehrm/overrides.zcml
Products/plonehrm/permissions.zcml
Products/plonehrm/profiles.zcml
Products/plonehrm/rebuild_i18n.sh
Products/plonehrm/setuphandlers.py
Products/plonehrm/tool.gif
Products/plonehrm/utils.py
Products/plonehrm/validator.py
Products/plonehrm/version.txt
Products/plonehrm/browser/__init__.py
Products/plonehrm/browser/absence.pt
Products/plonehrm/browser/absence.py
Products/plonehrm/browser/absence_overview.pt
Products/plonehrm/browser/absence_overview.py
Products/plonehrm/browser/absences.pt
Products/plonehrm/browser/altviews.pt
Products/plonehrm/browser/checklist.pt
Products/plonehrm/browser/configure.zcml
Products/plonehrm/browser/csv_import.pt
Products/plonehrm/browser/csv_import.py
Products/plonehrm/browser/dummy.txt
Products/plonehrm/browser/employee.pt
Products/plonehrm/browser/employee.py
Products/plonehrm/browser/employee_viewletmanager.pt
Products/plonehrm/browser/employees.pt
Products/plonehrm/browser/facebook.pt
Products/plonehrm/browser/file.kss
Products/plonehrm/browser/file.pt
Products/plonehrm/browser/file.py
Products/plonehrm/browser/file_kss.py
Products/plonehrm/browser/improvements.pt
Products/plonehrm/browser/inactive_employees.pt
Products/plonehrm/browser/interfaces.py
Products/plonehrm/browser/managers.py
Products/plonehrm/browser/menu.py
Products/plonehrm/browser/parameters.pt
Products/plonehrm/browser/personaldata.pt
Products/plonehrm/browser/personaldata_viewlet.pt
Products/plonehrm/browser/personaldata_worklocation_viewlet.pt
Products/plonehrm/browser/plonehrm.css
Products/plonehrm/browser/substitution.py
