Metadata-Version: 1.0
Name: Products.plonehrm
Version: 2.13
Summary: Human Resource Management in Plone
Home-page: UNKNOWN
Author: Zest Software
Author-email: info@zestsoftware.nl
License: GPL
Platform: UNKNOWN
Classifier: Framework :: Plone
Classifier: Programming Language :: Python
Classifier: Topic :: Software Development :: Libraries :: Python Modules
